Metadata-Version: 2.1
Name: devdash
Version: 0.9
Summary: Automatic developer dashboard
Home-page: https://github.com/hamelin/devdash
Author: Benoit Hamelin
License: MIT
Keywords: Development,Dashboard,Jupyter
Platform: UNKNOWN
Classifier: Development Status :: 4 - Beta
Classifier: Intended Audience :: Developers
Classifier: License :: OSI Approved :: MIT License
Classifier: Framework :: Jupyter
Classifier: Programming Language :: Python :: 3
Classifier: Programming Language :: Python :: 3.7
Classifier: Programming Language :: Python :: 3.8
Classifier: Programming Language :: Python :: 3.9
Classifier: Programming Language :: Python :: 3.10
Classifier: Topic :: Software Development
Classifier: Topic :: Software Development :: Quality Assurance
Classifier: Topic :: Software Development :: User Interfaces
License-File: LICENSE
